LICENSE
MANIFEST.in
README
cumulus
setup.py
cumulus.egg-info/PKG-INFO
cumulus.egg-info/SOURCES.txt
cumulus.egg-info/dependency_links.txt
cumulus.egg-info/not-zip-safe
cumulus.egg-info/requires.txt
cumulus.egg-info/top_level.txt
cumulus_ds/__init__.py
cumulus_ds/__init__.pyc
cumulus_ds/bundle_manager.py
cumulus_ds/bundle_manager.pyc
cumulus_ds/connection_handler.py
cumulus_ds/connection_handler.pyc
cumulus_ds/deployment_manager.py
cumulus_ds/deployment_manager.pyc
cumulus_ds/exceptions.py
cumulus_ds/exceptions.pyc
cumulus_ds/settings.conf
cumulus_ds/terminal_size.py
cumulus_ds/terminal_size.pyc
cumulus_ds/config/__init__.py
cumulus_ds/config/__init__.pyc
cumulus_ds/config/command_line_options.py
cumulus_ds/config/command_line_options.pyc
cumulus_ds/config/config_file.py
cumulus_ds/config/config_file.pyc
cumulus_ds/helpers/__init__.py
cumulus_ds/helpers/__init__.pyc
cumulus_ds/helpers/stack.py
cumulus_ds/helpers/stack.pyc