Metadata-Version: 1.1
Name: cumulus
Version: 1.4.0
Summary: Cumulus Deployment Suite for Amazon Web Services
Home-page: http://www.skymillsolutions.com
Author: Sebastian Dahlgren
Author-email: sebastian.dahlgren@skymill.se
License: Apache Software License
Keywords: cumulus cloudformation amazon web services
Platform: Any
Classifier: Development Status :: 4 - Beta
Classifier: Environment :: Console
Classifier: License :: OSI Approved :: Apache Software License
Classifier: Operating System :: OS Independent
Classifier: Programming Language :: Python
